.gitignore
LICENSE
MANIFEST.in
README.md
setup.py
streamlit_graphic_slider/__init__.py
streamlit_graphic_slider/__version__.py
streamlit_graphic_slider/component.py
streamlit_graphic_slider/sample_app.py
streamlit_graphic_slider.egg-info/PKG-INFO
streamlit_graphic_slider.egg-info/SOURCES.txt
streamlit_graphic_slider.egg-info/dependency_links.txt
streamlit_graphic_slider.egg-info/requires.txt
streamlit_graphic_slider.egg-info/top_level.txt
streamlit_graphic_slider/frontend/build/asset-manifest.json
streamlit_graphic_slider/frontend/build/bootstrap.min.css
streamlit_graphic_slider/frontend/build/index.html
streamlit_graphic_slider/frontend/build/precache-manifest.165b9d4e73fd2dbe42e4a7bdf06bbb2d.js
streamlit_graphic_slider/frontend/build/service-worker.js
streamlit_graphic_slider/frontend/build/static/js/2.1dbb1af8.chunk.js
streamlit_graphic_slider/frontend/build/static/js/2.1dbb1af8.chunk.js.LICENSE.txt
streamlit_graphic_slider/frontend/build/static/js/2.1dbb1af8.chunk.js.map
streamlit_graphic_slider/frontend/build/static/js/main.50ae3759.chunk.js
streamlit_graphic_slider/frontend/build/static/js/main.50ae3759.chunk.js.map
streamlit_graphic_slider/frontend/build/static/js/runtime-main.11ec9aca.js
streamlit_graphic_slider/frontend/build/static/js/runtime-main.11ec9aca.js.map